[
{"name": "Kivi Paket 250 g", "price": "3,49 TL"},
{"name": "Pırasa kg", "price": "3,99 TL"},
{"name": "Ayva Pazar kg", "price": "4,99 TL"},
{"name": "Soğan Kuru kg", "price": "1,79 TL"},
{"name": "Limon Mayer kg", "price": "2,99 TL"},
{"name": "Sıkma Portakal kg", "price": "4,99 TL"},
{"name": "Domates Pazar kg", "price": "3,79 TL"},
{"name": "Mandalina Satsuma Kg", "price": "6,99 TL"},
{"name": "Çengelköy Salatalık kg", "price": "4,99 TL"},
{"name": "Beyaz Lahana kg", "price": "3,25 TL"},
{"name": "Şalgam", "price": "5,95 TL"},
{"name": "Yerli Muz kg", "price": "9,90 TL"},
{"name": "Roka Adet", "price": "2,75 TL"},
{"name": "Kara Lahana kg", "price": "4,45 TL"},
{"name": "Kıvırcık Salata Adet", "price": "4,75 TL"},
{"name": "Turp Siyah", "price": "4,75 TL"},
{"name": "Göbek Salata Adet", "price": "6,25 TL"},
{"name": "Havuç kg", "price": "5,95 TL"},
{"name": "Beyaz Turp", "price": "5,95 TL"},
{"name": "Havuç Paket 1000 g Adet", "price": "6,95 TL"},
{"name": "Soğan Yeni Hasat kg", "price": "1,99 TL"},
{"name": "Patates Yemeklik kg", "price": "4,95 TL"},
{"name": "Çalı Fasulye Kg", "price": "16,90 TL"},
{"name": "Patlıcan Kemer kg", "price": "13,95 TL"},
{"name": "Bal Kabağı Soyulmuş (1200-1700gr)", "price": "10,90 TL"},
{"name": "Salatalık kg", "price": "6,99 TL"},
{"name": "Biber Sivri kg", "price": "17,90 TL"},
{"name": "Çarliston Biber kg", "price": "11,90 TL"},
{"name": "Enginar 4'lü", "price": "27,60 TL"},
{"name": "Karpuz  kg", "price": "2,99 TL"},
{"name": "Kivi kg", "price": "19,99 TL"},
{"name": "Armut Deveci Pazar kg", "price": "7,90 TL"},
{"name": "Avokado Adet", "price": "9,95 TL"},
{"name": "Ananas Adet", "price": "22,95 TL"},
{"name": "Kuru Sarımsak Kg", "price": "14,90 TL"},
{"name": "Kereviz Yapraklı Kg", "price": "7,99 TL"},
{"name": "Tatlı Patates", "price": "29,95 TL"},
{"name": "Beyaz Soğan 1 kg", "price": "5,99 TL"},
{"name": "Yer Elması", "price": "8,99 TL"},
{"name": "Tatlı Patates İthal kg", "price": "29,95 TL"},
{"name": "Soğan File kg", "price": "3,99 TL"},
{"name": "Taze Tatlı Patates Paket Adet", "price": "9,75 TL"},
{"name": "SARMISAK KURU KG", "price": "19,90 TL"},
{"name": "Soğan Mor kg", "price": "4,99 TL"},
{"name": "Reyhan", "price": "4,25 TL"},
{"name": "Mini Kuşkonmaz (Asparagus Tips", "price": "69,95 TL"},
{"name": "Kuzu Kulağı Demet", "price": "3,75 TL"},
{"name": "Deniz Börülcesi Adet", "price": "3,95 TL"},
{"name": "Nane Adet", "price": "3,25 TL"},
{"name": "Tere Adet", "price": "3,45 TL"},
{"name": "Taze Fesleğen", "price": "4,45 TL"},
{"name": "Pazı Adet", "price": "4,75 TL"},
{"name": "Dereotu Adet", "price": "2,25 TL"},
{"name": "Taze Fesleğen Adet", "price": "9,95 TL"},
{"name": "Maydanoz Adet", "price": "2,25 TL"},
{"name": "Domates Cheery Organik", "price": "35,99 TL"},
{"name": "Organik Patates kg", "price": "22,99 TL"},
{"name": "Organik Kuru Soğan", "price": "18,99 TL"},
{"name": "Karnabahar Organik", "price": "26,99 TL"},
{"name": "Salatalık Organik", "price": "24,99 TL"},
{"name": "Organik Domates kg", "price": "24,99 TL"},
{"name": "Biber Dolmalık Organik", "price": "29,99 TL"},
{"name": "Organik Havuç", "price": "21,99 TL"},
{"name": "Brokoli Organik", "price": "34,99 TL"},
{"name": "Organik Dereotu", "price": "9,99 TL"},
{"name": "Fasulye Taze Organik", "price": "35,99 TL"},
{"name": "Kıvırcık Organik", "price": "13,99 TL"},
{"name": "Kabak Organik", "price": "25,99 TL"},
{"name": "Çengelköy Organik Salatalık", "price": "24,99 TL"},
{"name": "Semizotu Adet", "price": "4,95 TL"},
{"name": "Kurutulmus Dolma Biber Adet", "price": "15,90 TL"},
{"name": "Taze Mısır Açık Adet", "price": "2,20 TL"},
{"name": "Sarıkız Mantarı Kuru 35 g", "price": "19,90 TL"},
{"name": "Kurutulmuş Dilim Domates", "price": "17,45 TL"},
{"name": "Kabak Sakız kg", "price": "9,99 TL"},
{"name": "Kabak Dolmalık kg", "price": "17,90 TL"},
{"name": "Borozan Mantarı Kuru 35 g", "price": "19,90 TL"},
{"name": "Mısır Kavanoz 350 g", "price": "6,49 TL"},
{"name": "Bostan Patlıcan kg", "price": "16,90 TL"},
{"name": "Kayseri Patlıcan kg", "price": "22,90 TL"},
{"name": "Kuzu Göbeği Mantarı Kuru 40 g", "price": "69,90 TL"},
{"name": "Kurutulmus Acı Biber Paket", "price": "14,90 TL"},
{"name": "Brokoli  kg", "price": "11,90 TL"},
{"name": "Kırmızı Turp kg", "price": "4,75 TL"},
{"name": "Japon Turp", "price": "4,95 TL"},
{"name": "Kıl Biber kg", "price": "19,90 TL"},
{"name": "Karnabahar kg", "price": "4,99 TL"},
{"name": "Fındık Turp Demet", "price": "4,45 TL"},
{"name": "Erüst Taze Baharatlar Adet", "price": "9,95 TL"},
{"name": "Verita Taze Meyve Salatası 200 g", "price": "29,95 TL"},
{"name": "Havuç Siyah", "price": "5,95 TL"},
{"name": "Domates Şeker 250  g", "price": "8,95 TL"},
{"name": "Dolma Biber Kg", "price": "8,99 TL"},
{"name": "Kıl Sivri Biber Paket", "price": "23,90 TL"},
{"name": "Lolorosso Adet", "price": "4,75 TL"},
{"name": "Alabaş Turp kg", "price": "6,95 TL"},
{"name": "Domates Salkım Paket", "price": "13,90 TL"},
{"name": "Brokoli Paket 400 g", "price": "9,90 TL"},
{"name": "Dilimlenmiş Hindistan Cevizi 200 g", "price": "29,95 TL"},
{"name": "Taze Soğan Demet", "price": "3,75 TL"},
{"name": "Jalepon Biber kg", "price": "21,90 TL"},
{"name": "Pancar kg", "price": "5,75 TL"},
{"name": "Nar Taneleri 200 g", "price": "24,95 TL"},
{"name": "Soyulmuş Haşlanmış Pancar 500 G Adet", "price": "24,90 TL"},
{"name": "Domates Sera kg", "price": "10,90 TL"},
{"name": "Renkli Dolma Biber kg", "price": "15,90 TL"},
{"name": "Kırmızı Lahana kg", "price": "6,45 TL"},
{"name": "Köy Biberi kg", "price": "13,90 TL"},
{"name": "Çin Marulu", "price": "7,95 TL"},
{"name": "Domates Pembe kg", "price": "9,99 TL"},
{"name": "Domates Salkım kg", "price": "12,90 TL"},
{"name": "Marul Adet", "price": "5,75 TL"},
{"name": "Domates Kokteyl kg", "price": "11,90 TL"},
{"name": "Taze Fasulye Kavanoz 560 g", "price": "12,99 TL"},
{"name": "Enginar Küçük Kavanoz 600 g", "price": "39,95 TL"},
{"name": "Kereviz Sapı Adet", "price": "9,95 TL"},
{"name": "Domates Sosu Kavanoz 590 g", "price": "18,99 TL"},
{"name": "Enginar 4'lü Şişe Kavanoz 370 g", "price": "25,99 TL"},
{"name": "Bal Kabağı Püresi Kavanoz 320 g", "price": "8,49 TL"},
{"name": "Enginar Püresi Kavonoz 150 g", "price": "20,99 TL"},
{"name": "Kereviz Kavanoz 930 g", "price": "26,90 TL"},
{"name": "Acı Biber Salçası 600 g", "price": "22,45 TL"},
{"name": "Enginar Büyük Kavanoz 930 g", "price": "52,49 TL"},
{"name": "Bamya Kızartmalık Kavanoz 800 g", "price": "19,99 TL"},
{"name": "Tatlı Biber Salçası Kavanoz 600 g", "price": "22,45 TL"},
{"name": "Garnitür Kavanoz 590 g", "price": "16,49 TL"},
{"name": "Agrotalya Tatlı Mısır 400 g", "price": "34,90 TL"},
{"name": "Enginar Baby Kavanoz 300 g", "price": "29,99 TL"},
{"name": "Bayrampaşa Soyulmuş Çanak Enginar 5'li", "price": "34,50 TL"},
{"name": "Tombul Bamya Kavanoz 530 g", "price": "31,99 TL"},
{"name": "Domates Salçası Kavanoz 590 g", "price": "18,99 TL"},
{"name": "Bezelye Kavanoz 600 g", "price": "16,49 TL"},
{"name": "Taze Enginar (Temizlenmiş)", "price": "6,90 TL"},
{"name": "Finike Gurme Portakal kg", "price": "9,99 TL"},
{"name": "Mandalina Satsuma İzmir kg", "price": "10,90 TL"},
{"name": "Lime kg", "price": "64,95 TL"},
{"name": "Greyfurt Kanlı kg", "price": "7,45 TL"},
{"name": "Lime 3'lü Paket", "price": "19,95 TL"},
{"name": "Washington Portakal kg", "price": "6,99 TL"},
{"name": "Organik Mandalina kg", "price": "28,99 TL"},
{"name": "Kavun Honeydew kg", "price": "24,95 TL"},
{"name": "Organik Portakal", "price": "22,99 TL"},
{"name": "Elma Starking kg", "price": "6,99 TL"},
{"name": "Elma Starking Paket gurme", "price": "14,90 TL"},
{"name": "Limon Organik kg", "price": "27,99 TL"},
{"name": "Kestane kg", "price": "49,95 TL"},
{"name": "Elma Grany Ekonomik kg", "price": "6,45 TL"},
{"name": "Organik Yerli Muz kg", "price": "29,99 TL"},
{"name": "Elma Golden Paket", "price": "13,90 TL"},
{"name": "Nar kg", "price": "8,99 TL"},
{"name": "Üzüm Red Globe İthal kg", "price": "54,95 TL"},
{"name": "Arapkızı Elma kg", "price": "10,90 TL"},
{"name": "Verita Böğürtlen Paket 125 g", "price": "69,95 TL"},
{"name": "Armut Santa Maria kg", "price": "14,95 TL"},
{"name": "Karyağdı Armudu kg", "price": "9,90 TL"},
{"name": "Siyah Karpuz kg", "price": "3,49 TL"},
{"name": "Amasya Elma kg", "price": "9,99 TL"},
{"name": "Verita Ahududu Frambuaz 125 g", "price": "69,95 TL"},
{"name": "Mini Karpuz", "price": "3,99 TL"},
{"name": "Çekirdeksiz Karpuz ", "price": "3,49 TL"},
{"name": "Fuji Elma Kg", "price": "7,95 TL"},
{"name": "Anjelika Erik kg", "price": "19,90 TL"},
{"name": "Golden Elma kg", "price": "7,95 TL"},
{"name": "Armut Deveci kg", "price": "12,95 TL"},
{"name": "Red Globe Üzüm  kg", "price": "16,90 TL"},
{"name": "Elma Pink Lady kg", "price": "8,90 TL"},
{"name": "Kavun Organik", "price": "6,99 TL"},
{"name": "Çilek Paket 500 g", "price": "28,90 TL"},
{"name": "Papaya Gurme Yemeye Hazır Adet", "price": "79,95 TL"},
{"name": "Verita Dr. Blue Blueberry 125 g", "price": "44,95 TL"},
{"name": "Verita Redberry-Frenk Üzümü 125 g", "price": "69,95 TL"},
{"name": "Zencefil kg", "price": "69,95 TL"},
{"name": "Zencefil Taze kg", "price": "69,95 TL"},
{"name": "Trabzon Hurması kg", "price": "10,95 TL"},
{"name": "Çarkıfelek 130 g", "price": "39,95 TL"},
{"name": "Hindiba", "price": "39,95 TL"},
{"name": "Zencefil 250 g Adet", "price": "21,95 TL"},
{"name": "Tamarind Demirhindi 225 g", "price": "34,95 TL"},
{"name": "Mango Adet*", "price": "17,95 TL"},
{"name": "Zerdeçal Paket 150 g", "price": "14,95 TL"},
{"name": "Altın Çilek 100 g Adet", "price": "34,95 TL"},
{"name": "Hindistan Cevizi Adet", "price": "14,95 TL"},
{"name": "Dilimlenmiş Taze Mango 125 g", "price": "29,95 TL"},
{"name": "Pomelo adet", "price": "49,95 TL"},
{"name": "İthal Muz kg", "price": "23,95 TL"},
{"name": "Blueberry 125 g Adet", "price": "39,95 TL"},
{"name": "Ananas Adet", "price": "22,95 TL"},
{"name": "Yaban Mersini 125 g", "price": "39,95 TL"},
{"name": "Mango Gurme Yemeğe Hazır Adet", "price": "29,95 TL"},
{"name": "Avokado Gurme Yemeğe Hazır Paket 2 'li", "price": "39,95 TL"},
{"name": "Avokado Gurme Yemeye Hazır Adet", "price": "20,95 TL"},
{"name": "Mango Adet", "price": "17,95 TL"},
{"name": " Mantar Dilim 400 g", "price": "9,90 TL"},
{"name": "Domates kg", "price": "9,90 TL"},
{"name": "Şeftali kg", "price": "12,90 TL"},
{"name": "Elma Starking Ekonomik kg", "price": "6,45 TL"},
{"name": "Kavun Galya", "price": "3,45 TL"},
{"name": "Taze Patates", "price": "8,90 TL"},
{"name": "Sarımsak Bohça 250 g", "price": "8,49 TL"},
{"name": "Taşköprü Sarımsak Örgü kg", "price": "33,90 TL"},
{"name": "Siyah Sarımsak 65Gr", "price": "20,90 TL"},
{"name": "Patates Yerli Tohum kg", "price": "3,25 TL"},
{"name": "Soğan Arpacık 250 g Adet", "price": "4,45 TL"},
{"name": "Soğan File 1 kg Adet", "price": "3,79 TL"},
{"name": "Sarımsak Kuru 250 g", "price": "11,90 TL"},
{"name": "Soğan Mor 1 kg File", "price": "7,45 TL"},
{"name": "Arpacık Soğan Paket 500 gr", "price": "13,90 TL"},
{"name": "Taşköprü Sarımsak Sepet Adet", "price": "36,90 TL"},
{"name": "Soğan Kuru kg", "price": "2,45 TL"},
{"name": "Kızartmalık Patates 3 kg", "price": "17,90 TL"},
{"name": "Pazı", "price": "99,00 TL"},
{"name": "Erüst Frenk Maydanoz Adet", "price": "11,90 TL"},
{"name": "Erüst Kuzu Kulağı 150 g", "price": "15,90 TL"},
{"name": "Erüst Baby Roka 125 g", "price": "15,90 TL"},
{"name": "Kabak Mix 2 Yenilebilir", "price": "7,99 TL"},
{"name": "Mantar İstiridye 200 g", "price": "10,49 TL"},
{"name": "Taze Fasulye kg", "price": "16,95 TL"},
{"name": "Patlıcan Paket kg", "price": "17,90 TL"},
{"name": "Patlıcan Kemer Pazar", "price": "7,65 TL"},
{"name": "Mantar Kestane 350 g", "price": "11,90 TL"},
{"name": "Semizotu 150 G Adet", "price": "10,50 TL"},
{"name": "Kurutulmuş Dolmalık Patlıcan Adet", "price": "15,90 TL"},
{"name": "Mantar Izgaralık 1000 g", "price": "24,90 TL"},
{"name": "Mantar Shitake 200 g", "price": "21,90 TL"},
{"name": "Kuru Patlıcan", "price": "37,90 TL"},
{"name": "Mantar 300 g", "price": "8,99 TL"},
{"name": "Kabak Paket", "price": "13,90 TL"},
{"name": "Kuru Dereotu  kg", "price": "89,90 TL"},
{"name": "Kabak Butternut", "price": "6,50 TL"},
{"name": "Kabak Bal Hokkaido", "price": "8,99 TL"},
{"name": "Börülce Fasulye", "price": "24,90 TL"},
{"name": "Kabak Süs Mix ", "price": "8,75 TL"},
{"name": "Açık Mantar kg", "price": "19,90 TL"},
{"name": "Kuru Maydonoz kg", "price": "89,90 TL"},
{"name": "Bezelye", "price": "9,45 TL"},
{"name": "Biberiye 25 gr", "price": "7,50 TL"},
{"name": "Soya Filizi 125 g Adet", "price": "15,90 TL"},
{"name": "Cheery Domates", "price": "23,90 TL"},
{"name": "Sivri Biber Acı Pazar kg", "price": "9,99 TL"},
{"name": "Domates Beef kg", "price": "9,90 TL"},
{"name": "Domates Turşuluk", "price": "6,45 TL"},
{"name": "Biber Sılı Kırmızı kg", "price": "29,90 TL"},
{"name": "Domates Cherry 250 gr", "price": "13,50 TL"},
{"name": "Erüst Çıtır Marul 100 g", "price": "14,95 TL"},
{"name": "Biber Çarliston Paket", "price": "16,90 TL"},
{"name": "Salatalık Pazar kg", "price": "3,75 TL"},
{"name": "Domates Yerli Bonbon 400 g", "price": "10,90 TL"},
{"name": "Domates Kahvaltılık Yerli Tohum kg", "price": "8,90 TL"},
{"name": "Fençel", "price": "9,99 TL"},
{"name": "Erüst Kokteyl Domates 500 gr", "price": "11,90 TL"},
{"name": "Salatalık Çengelköy Paket kg", "price": "7,49 TL"},
{"name": "Domates kg", "price": "5,45 TL"},
{"name": "Salata Maskolin Adet", "price": "14,95 TL"},
{"name": "Domates Kokteyl Paket", "price": "8,99 TL"},
{"name": "Domates Kokteyl Salkım Paket Gurme", "price": "28,90 TL"},
{"name": "Domates Salkım Pazar kg", "price": "8,95 TL"},
{"name": "Salatalık Çengel Paket Gurme 700 g", "price": "8,99 TL"},
{"name": "Domates Salkım Paket", "price": "16,90 TL"},
{"name": "Dolma Biber Paket", "price": "15,90 TL"},
{"name": "Karışık Akdeniz Salata 150 g Adet", "price": "14,95 TL"},
{"name": "BIBER SIVRI GURME", "price": "12,90 TL"},
{"name": "Erust Taze Baharat (Rozmarin, Kekik, Adaçayı) ", "price": "7,50 TL"},
{"name": "Acur", "price": "8,90 TL"},
{"name": "Biber Top", "price": "9,99 TL"},
{"name": "Domates Antalya kg", "price": "7,99 TL"},
{"name": "Domates Pembe Tabak Gurme", "price": "16,90 TL"},
{"name": "Domates Tekli Lüx Paket kg", "price": "11,90 TL"},
{"name": "Cin Biber 100 g Adet", "price": "9,90 TL"},
{"name": "Domates Kumato kg", "price": "11,90 TL"},
{"name": "Soyulmuş Arpacık Soğan 250 g Adet", "price": "18,95 TL"},
{"name": "Soyulmus Arpacık 500 g Adet", "price": "29,99 TL"},
{"name": "Soyulmuş Sarımsak 60 g", "price": "10,90 TL"},
{"name": "Erüst Mini Kabak 250 gr", "price": "14,50 TL"},
{"name": "Soyulmuş Mor Soğan 250 gr", "price": "6,49 TL"},
{"name": "Erüst Mini Ispanak 150 g Adet", "price": "15,75 TL"},
{"name": "Erüs Mini Patlıcan", "price": "14,50 TL"},
{"name": "Yarı Kurutulmuş Domates 200 g", "price": "12,90 TL"},
{"name": "Euro Fresh Kök Ispanak 500 g", "price": "11,95 TL"},
{"name": "Paket Ispanak 700 g", "price": "17,50 TL"},
{"name": "File Limon Adet 500 g", "price": "3,75 TL"},
{"name": "Mandalina Murcot Gurme kg", "price": "9,99 TL"},
{"name": "Mandalina Murcot kg", "price": "9,99 TL"},
{"name": "File Sıkma Portakal kg", "price": "9,90 TL"},
{"name": "Limon Enterdonat", "price": "6,99 TL"},
{"name": "Mandalina kg", "price": "5,95 TL"},
{"name": "Portakal kg", "price": "6,95 TL"},
{"name": "Limon Dökme kg", "price": "3,90 TL"},
{"name": "Naturel Mandalina", "price": "3,99 TL"},
{"name": "Limon Naturel", "price": "8,75 TL"},
{"name": "Limon File kg", "price": "9,99 TL"},
{"name": "Greyfurt kg", "price": "5,95 TL"},
{"name": "Valensiya Portakal Kg", "price": "11,95 TL"},
{"name": "Beyaz Greyfurt kg", "price": "8,49 TL"},
{"name": "SEFTALI 50-65MM", "price": "10,90 TL"},
{"name": "Erik Angelina Paket", "price": "24,90 TL"},
{"name": "Elma Granny Smith Gurme kg", "price": "10,90 TL"},
{"name": "Nar Pazar", "price": "5,45 TL"},
{"name": "Nar İri Paketli", "price": "9,90 TL"},
{"name": "Ayva Paket Gurme", "price": "15,90 TL"},
{"name": "Mürdüm Erik", "price": "10,90 TL"},
{"name": "Golden Elma", "price": "5,95 TL"},
{"name": "Kayısı Paket", "price": "12,90 TL"},
{"name": "Bayramiç Beyaz Nektarin kg", "price": "99,00 TL"},
{"name": "Armut Deveci Gurme Paket", "price": "17,90 TL"},
{"name": "Elma Golden Gurme", "price": "9,49 TL"},
{"name": "Şeftali", "price": "10,90 TL"},
{"name": "Erik Frezee", "price": "10,90 TL"},
{"name": "Kiraz Gurme", "price": "39,90 TL"},
{"name": "Elma Fujı Paket kg", "price": "16,90 TL"},
{"name": "Çilek Paket Gurme kg", "price": "19,90 TL"},
{"name": "Muşmula kg", "price": "13,90 TL"},
{"name": "Armut Margaret kg", "price": "8,49 TL"},
{"name": "Armut Santa Maria Gurme kg", "price": "12,90 TL"},
{"name": "Siyah Üzüm kg", "price": "14,90 TL"},
{"name": "Fuji Elma", "price": "6,99 TL"},
{"name": "Antep Karası Üzüm kg", "price": "11,90 TL"},
{"name": "Gala Elma Kg", "price": "7,75 TL"},
{"name": "Kayısı Şekerpare kg", "price": "28,90 TL"},
{"name": "Malta Erik", "price": "19,90 TL"},
{"name": "Elma Starking Gurme kg", "price": "9,90 TL"},
{"name": "Armut", "price": "19,90 TL"},
{"name": "Elma Amasya Paket kg", "price": "18,90 TL"},
{"name": "Erik Sarı", "price": "12,90 TL"},
{"name": "Erik Can Paket", "price": "29,90 TL"},
{"name": "Çilek kg", "price": "28,90 TL"},
{"name": "Armut Etruska kg", "price": "19,90 TL"},
{"name": "Akça Armut kg", "price": "23,90 TL"},
{"name": "Elma Granny Smith kg", "price": "11,90 TL"},
{"name": "Kavun Kelek", "price": "8,99 TL"},
{"name": "Siyah İncir kg", "price": "19,95 TL"},
{"name": "Elma Golden Pazar kg", "price": "8,95 TL"},
{"name": "Elma Star Pazar kg", "price": "0,01 TL"},
{"name": "Armut Santa Maria Pazar kg", "price": "8,90 TL"},
{"name": "Dut Kara", "price": "19,90 TL"},
{"name": "Elma Modi", "price": "5,99 TL"},
{"name": "Ayva Kg", "price": "10,90 TL"},
{"name": "Razaki Üzüm kg", "price": "10,90 TL"},
{"name": "Beyaz Üzüm", "price": "13,90 TL"},
{"name": "Armut Ankara Gurme Paket", "price": "13,90 TL"},
{"name": "Hünnap kg", "price": "29,90 TL"},
{"name": "Nektarin Beyaz kg", "price": "19,90 TL"},
{"name": "Nektarin kg", "price": "13,90 TL"},
{"name": "Kayısı", "price": "77,90 TL"},
{"name": "Nektarin Paket", "price": "14,90 TL"},
{"name": "Organik Yaban Mersini Adet", "price": "46,90 TL"},
{"name": "Pepino", "price": "7,99 TL"},
{"name": "Yerli Muz Paket Gurme kg", "price": "18,90 TL"},
{"name": "Pitahaya Ejder Meyvesi", "price": "32,90 TL"},
{"name": "Kumkuat Kg", "price": "22,90 TL"},
{"name": "Pitahaya Ejder Meyvesi Adet", "price": "29,90 TL"},
{"name": null, "price": null}
]